[
  {
    "id": 1,
    "slug": "esmeralda",
    "nombre": "La Esmeralda",
    "ciudad": "Flandes",
    "departamento": "Tolima",
    "tipo": "urbanizacion",
    "logo": "assets/images/boton-esmeralda.jpg.jpeg",
    "descripcion": "Urbanización abierta en Flandes, Tolima, cerca al Río Magdalena, con áreas para vivienda desde 72 m² ($38.000.000) y áreas industriales. Alta valorización, servicios básicos y facilidad de pago directa sin intereses.",
    "ubicacion": "Flandes, Tolima",
    "ubicacionTexto": "Estratégicamente ubicado en Flandes, Tolima, con fácil acceso vial desde Bogotá y Girardot. Zona de alto crecimiento inmobiliario.",
    "mapa": "https://www.google.com/maps?q=Flandes+Tolima&output=embed",
    "lat": 4.2912,
    "lng": -74.8165,
    "precioDesde": 38000000,
    "precioTexto": "$38.000.000",
    "area": "Desde 72 m²",
    "precioCat": "economico",
    "areaCat": "compacto",
    "caracteristicas": ["Urbanización abierta", "Áreas para vivienda e industriales", "Servicios básicos", "Financiación hasta 36 meses sin intereses"],
    "lotes": [
      { "label": "Vivienda · 6 × 12 m · 72 m²", "precio": 38000000 },
      { "label": "Vivienda · 7 × 14 m · 98 m²", "precio": 45000000 },
      { "label": "Industrial · 8.98 × 19.11 m", "precio": 76500000 },
      { "label": "Industrial · 8.54 × 33.45 m", "precio": 127555000 }
    ],
    "imagenes": [
      "assets/images/dron1.webp",
      "assets/images/dron2.webp",
      "assets/images/flandes1.webp",
      "assets/images/flandes2.webp",
      "assets/images/flandes3.webp",
      "assets/images/flandes4.webp"
    ],
    "pdfPrecios": "assets/pdf/tabla-valores-urbanizacion-la-esmeralda.pdf"
  },

  {
    "id": 2,
    "slug": "esmeralda-luxury",
    "nombre": "La Esmeralda Luxury",
    "ciudad": "Flandes",
    "departamento": "Tolima",
    "tipo": "condominio",
    "logo": "assets/images/boton-esmeralda-luxury.jpg.jpeg",
    "descripcion": "Condominio cerrado con lotes de 105 m² ($55.000.000) en Flandes, Tolima, y un área comercial disponible. Exclusividad, seguridad y valorización garantizada en una de las zonas de mayor desarrollo del país.",
    "ubicacion": "Flandes, Tolima",
    "ubicacionTexto": "Ubicado en Flandes, Tolima, en zona residencial con acceso controlado, vías internas pavimentadas y todos los servicios.",
    "mapa": "https://www.google.com/maps?q=Flandes+Tolima&output=embed",
    "lat": 4.2920,
    "lng": -74.8170,
    "precioDesde": 55000000,
    "precioTexto": "$55.000.000",
    "area": "105 m²",
    "precioCat": "premium",
    "areaCat": "mediano",
    "caracteristicas": ["Condominio cerrado", "Área comercial disponible", "Portería 24h", "Financiación directa sin intereses"],
    "lotes": [
      { "label": "7 × 15 m · 105 m²", "precio": 55000000 },
      { "label": "Comercial · 12.76 × 15 m", "precio": 91160000 }
    ],
    "imagenes": [
      "assets/images/boton-esmeralda-luxury.jpg.jpeg"
    ],
    "pdfPrecios": null
  },

  {
    "id": 3,
    "slug": "topacio",
    "nombre": "Topacio",
    "ciudad": "Flandes",
    "departamento": "Tolima",
    "tipo": "urbanizacion",
    "logo": "assets/images/boton-esmeralda-topacio.jpg.jpeg",
    "descripcion": "Urbanización en Flandes, Tolima, con lotes para vivienda desde 72 m² ($32.000.000) y áreas comerciales. Financiación directa, sin bancos y sin intereses. El punto de entrada ideal para tu primera inversión.",
    "ubicacion": "Flandes, Tolima",
    "ubicacionTexto": "En el municipio de Flandes, Tolima, con excelente conectividad y proyección de valorización a corto y mediano plazo.",
    "mapa": "https://www.google.com/maps?q=Flandes+Tolima&output=embed",
    "lat": 4.2900,
    "lng": -74.8155,
    "precioDesde": 32000000,
    "precioTexto": "$32.000.000",
    "area": "Desde 72 m²",
    "precioCat": "economico",
    "areaCat": "compacto",
    "caracteristicas": ["Urbanización abierta", "Áreas comerciales disponibles", "Precio accesible", "Financiación hasta 36 meses sin intereses"],
    "lotes": [
      { "label": "6 × 12 m · 72 m²", "precio": 32000000 },
      { "label": "6.5 × 12 m · 78 m²", "precio": 34700000 },
      { "label": "7 × 13 m · 91 m²", "precio": 38000000 },
      { "label": "7 × 14 m · 98 m²", "precio": 40000000 },
      { "label": "Comercial · 7 × 13 m", "precio": 45860000 },
      { "label": "Comercial · 19.44 × 10 m", "precio": 90608800 }
    ],
    "imagenes": [
      "assets/images/boton-esmeralda-topacio.jpg.jpeg"
    ],
    "pdfPrecios": "assets/pdf/tabla-valores-urbanizacion-topacio.pdf"
  },

  {
    "id": 4,
    "slug": "topacio-luxury",
    "nombre": "Topacio Luxury",
    "ciudad": "Flandes",
    "departamento": "Tolima",
    "tipo": "condominio",
    "logo": "assets/images/boton-esmeralda-topacio-luxury.jpg.jpeg",
    "descripcion": "Condominio cerrado de alto estándar en Flandes, Tolima. Lotes desde 98 m² ($45.000.000) con portería, zonas comunes y toda la documentación legal al día.",
    "ubicacion": "Flandes, Tolima",
    "ubicacionTexto": "Condominio residencial en zona exclusiva de Flandes, Tolima, con alta proyección de valorización y seguridad permanente.",
    "mapa": "https://www.google.com/maps?q=Flandes+Tolima&output=embed",
    "lat": 4.2930,
    "lng": -74.8180,
    "precioDesde": 45000000,
    "precioTexto": "$45.000.000",
    "area": "Desde 98 m²",
    "precioCat": "premium",
    "areaCat": "mediano",
    "caracteristicas": ["Condominio cerrado", "Zonas comunes", "Portería 24h", "Financiación directa"],
    "lotes": [
      { "label": "7 × 14 m · 98 m²", "precio": 45000000 },
      { "label": "8.83 × 14 m · 124 m²", "precio": 63000000 }
    ],
    "imagenes": [
      "assets/images/boton-esmeralda-topacio-luxury.jpg.jpeg"
    ],
    "pdfPrecios": "assets/pdf/tabla-valores-condominio-topacio-luxury.pdf"
  },

  {
    "id": 5,
    "slug": "puerta-de-oro",
    "nombre": "Puerta de Oro",
    "ciudad": "Flandes",
    "departamento": "Tolima",
    "tipo": "condominio",
    "logo": "assets/images/boton-puerta-de-oro.jpg.jpeg",
    "descripcion": "Condominio campestre con grandes lotes desde 500 m² ($120.000.000) en Flandes, Tolima. Servicios de agua, energía y alcantarillado. Entorno natural privilegiado a minutos del Río Magdalena.",
    "ubicacion": "Flandes, Tolima",
    "ubicacionTexto": "Ubicado en las afueras de Flandes, Tolima, en un entorno campestre con naturaleza, tranquilidad y alta valorización a largo plazo.",
    "mapa": "https://www.google.com/maps?q=Flandes+Tolima&output=embed",
    "lat": 4.2880,
    "lng": -74.8200,
    "precioDesde": 120000000,
    "precioTexto": "$120.000.000",
    "area": "Desde 500 m²",
    "precioCat": "premium",
    "areaCat": "grande",
    "caracteristicas": ["Condominio campestre", "Agua y energía", "Alcantarillado", "Lotes grandes"],
    "lotes": [
      { "label": "Campestre · 20 × 25 m · 500 m²", "precio": 120000000 },
      { "label": "Campestre · 20 × 35 m · 700 m²", "precio": 160000000 }
    ],
    "imagenes": [
      "assets/images/boton-puerta-de-oro.jpg.jpeg"
    ],
    "pdfPrecios": null
  },

  {
    "id": 8,
    "slug": "terrazas-de-alejandria-ii",
    "nombre": "Terrazas de Alejandría II Etapa",
    "ciudad": "Flandes",
    "departamento": "Tolima",
    "tipo": "condominio",
    "logo": "assets/images/boton-terrazas.jpg.jpeg",
    "descripcion": "Segunda etapa del condominio Terrazas de Alejandría en Flandes, Tolima. Lotes de 75 m² desde $80.000.000, con opción de lote + vivienda desde $210.000.000 y financiación directa sin intereses.",
    "ubicacion": "Flandes, Tolima",
    "ubicacionTexto": "Ubicado en Flandes, Tolima, zona de alta valorización con buena conectividad vial.",
    "mapa": "https://www.google.com/maps?q=Flandes+Tolima&output=embed",
    "lat": 4.2912,
    "lng": -74.8165,
    "precioDesde": 80000000,
    "precioTexto": "$80.000.000",
    "area": "75 m²",
    "precioCat": "premium",
    "areaCat": "compacto",
    "caracteristicas": ["Condominio cerrado", "Lote + vivienda disponible", "Financiación directa sin intereses", "Servicios básicos"],
    "lotes": [
      { "label": "6 × 12.5 m · 75 m²", "precio": 80000000 },
      { "label": "Lote + vivienda", "precio": 210000000 }
    ],
    "imagenes": [
      "assets/images/boton-terrazas.jpg.jpeg"
    ],
    "pdfPrecios": null
  }
]
